.gitignore
LICENSE
README.rst
gsl_packages.py
pyproject.toml
setup.py
tox.ini
.github/workflows/ci.yml
Include/pygsl_lite/arrayobject.h
Include/pygsl_lite/block_helpers.h
Include/pygsl_lite/block_helpers_numpy.h
Include/pygsl_lite/capsuletrunk.h
Include/pygsl_lite/compilers.h
Include/pygsl_lite/complex_helpers.h
Include/pygsl_lite/error_helpers.h
Include/pygsl_lite/errorno.h
Include/pygsl_lite/function_helpers.h
Include/pygsl_lite/general_helpers.h
Include/pygsl_lite/intern.h
Include/pygsl_lite/old_numpy_compat.h
Include/pygsl_lite/profile.h
Include/pygsl_lite/pygsl.h
Include/pygsl_lite/pygsl_features.h
Include/pygsl_lite/pygsl_features_config.h
Include/pygsl_lite/rng.h
Include/pygsl_lite/rng_helpers.h
Include/pygsl_lite/solver.h
Include/pygsl_lite/string_helpers.h
Include/pygsl_lite/transition.h
Include/pygsl_lite/utils.h
gsl_dist/__init__.py
gsl_dist/array_includes.py
gsl_dist/gsl_Extension.py
gsl_dist/gsl_Location.py
gsl_dist/swig_extension.py
pygsl_lite/__init__.py
pygsl_lite/_block.py
pygsl_lite/_callback.py
pygsl_lite/_generic_solver.py
pygsl_lite/_numobj.py
pygsl_lite/_version.py
pygsl_lite/block.py
pygsl_lite/errors.py
pygsl_lite/gsl_function.py
pygsl_lite/gslwrap.py
pygsl_lite/interpolation.py
pygsl_lite/math.py
pygsl_lite/odeiv.py
pygsl_lite/odeiv2.py
pygsl_lite/roots.py
pygsl_lite/spline.py
pygsl_lite/vector.py
pygsl_lite.egg-info/PKG-INFO
pygsl_lite.egg-info/SOURCES.txt
pygsl_lite.egg-info/dependency_links.txt
pygsl_lite.egg-info/requires.txt
pygsl_lite.egg-info/top_level.txt
src/errortestmodule.c
src/block/gsl_block.i
src/block/gsl_block_char.i
src/block/gsl_block_complex.i
src/block/gsl_block_complex_float.i
src/block/gsl_block_double.i
src/block/gsl_block_float.i
src/block/gsl_block_generic.i
src/block/gsl_block_generic_typed.i
src/block/gsl_block_int.i
src/block/gsl_block_long.i
src/block/gsl_block_short.i
src/callback/chars.c
src/callback/function_helpers.c
src/callback/gsl_callback.i
src/callback/gsl_function_test.i
src/callback/gsl_multiroots.i
src/callback/gsl_odeiv.i
src/callback/gsl_odeiv2.i
src/callback/gsl_roots.i
src/callback/odeiv.ic
src/callback/odeiv_func2.ic
src/gslwrap/gsl_gslwrap.i
