Metadata-Version: 2.1
Name: pygsl_lite
Version: 0.1.6
Summary: Minimal GNU Scientific Library Interface
Author: Sergei Ossokine
License: GPL-2.0-or-later
Project-URL: homepage, https://github.com/AEI-ACR/pygsl_lite
Requires-Python: >=3.8
License-File: LICENSE
Requires-Dist: numpy>=1.23.0
